README.md
setup.py
perch/__init__.py
perch/cli.py
perch/endpoints.py
perch/main.py
perch/version.py
perch_security.egg-info/PKG-INFO
perch_security.egg-info/SOURCES.txt
perch_security.egg-info/dependency_links.txt
perch_security.egg-info/entry_points.txt
perch_security.egg-info/requires.txt
perch_security.egg-info/top_level.txt