Metadata-Version: 1.1
Name: perch-security
Version: 0.0.1
Summary: Perch Security python client and command line tools
Home-page: https://github.com/usePF/perch-client
Author: Nick Hagianis
Author-email: dev@perchsecurity.com
License: MIT
Platform: UNKNOWN
Classifier: Programming Language :: Python :: 2.7
Classifier: Programming Language :: Python :: 3.5
Classifier: Programming Language :: Python :: 3.6
